neureval/__init__.py
neureval/best_nclust_cv_confounds.py
neureval/internal_baselines_confounds.py
neureval/param_selection_confounds.py
neureval/relative_validation_confounds.py
neureval/utils.py
neureval/visualization.py
neureval-1.1.1.dist-info/LICENSE
neureval-1.1.1.dist-info/METADATA
neureval-1.1.1.dist-info/WHEEL
neureval-1.1.1.dist-info/top_level.txt
neureval-1.1.1.dist-info/RECORD
