Metadata-Version: 2.2
Name: neureval
Version: 1.1.1
Summary: Stability-based relative clustering validation algorithm for neuroimaging data
Home-page: https://github.com/fede-colombo/NeuReval
Download-URL: https://github.com/fede-colombo/NeuReval/releases/tag/v1.1.1
Author: Federica Colombo
Author-email: f.colombo8@studenti.unisr.it
Classifier: Programming Language :: Python :: 3
Classifier: License :: OSI Approved :: MIT License
Classifier: Operating System :: OS Independent
Requires-Python: >=3.6
License-File: LICENSE
Requires-Dist: numpy
Requires-Dist: scipy
Requires-Dist: scikit-learn
Requires-Dist: umap-learn
Requires-Dist: matplotlib
Dynamic: author
Dynamic: author-email
Dynamic: classifier
Dynamic: description
Dynamic: description-content-type
Dynamic: download-url
Dynamic: home-page
Dynamic: requires-dist
Dynamic: requires-python
Dynamic: summary
